promptworks/__init__.py
promptworks/interfaces.py
promptworks/prompt.py
promptworks/prompthistory.py
promptworks/components/__init__.py
promptworks/components/chathistoryitem.py
promptworks/components/localfile.py
promptworks/components/localtime.py
promptworks/components/plaintext.py
promptworks/renderers/__init__.py
promptworks/renderers/jsonrenderer.py
promptworks/renderers/xmlrenderer.py
promptworks-0.1.0.dist-info/METADATA
promptworks-0.1.0.dist-info/WHEEL
promptworks-0.1.0.dist-info/entry_points.txt
promptworks-0.1.0.dist-info/licenses/LICENSE
promptworks-0.1.0.dist-info/RECORD
